setup.py
page_clustering/__init__.py
page_clustering/clustering.py
page_clustering/features.py
page_clustering.egg-info/PKG-INFO
page_clustering.egg-info/SOURCES.txt
page_clustering.egg-info/dependency_links.txt
page_clustering.egg-info/requires.txt
page_clustering.egg-info/top_level.txt