Metadata-Version: 1.1
Name: page-clustering
Version: 0.0.1
Summary: Online k-means clustering of web pages
Home-page: https://github.com/scrapinghub/page_clustering
Author: Pedro Lopez-Adeva Fernandez-Layos
Author-email: pedro@scrapinghub.com
License: UNKNOWN
Keywords: crawler,scrapy,scrapely,web
Platform: UNKNOWN
Classifier: Development Status :: 4 - Beta
Classifier: Environment :: Console
Classifier: Intended Audience :: Developers
Classifier: License :: OSI Approved :: BSD License
Classifier: Operating System :: POSIX
Classifier: Programming Language :: Python
Classifier: Programming Language :: Python :: 2
Classifier: Programming Language :: Python :: 2.7
Classifier: Topic :: Internet :: WWW/HTTP
Classifier: Topic :: Software Development :: Libraries :: Python Modules
